<?xml version="1.0" encoding="UTF-8"?>
<gc:CodeList xmlns:gc="http://docs.oasis-open.org/codelist/ns/genericode/1.0/"
             xmlns:xsi="http://www.w3.org/2001/XMLSchema-instance"
             xmlns:xoev-cl-4="http://xoev.de/schemata/genericode/4">
   <Annotation>
      <Description>
         <xoev-cl-4:shortName>Aufgabenfeld</xoev-cl-4:shortName>
         <xoev-cl-4:codelistDescription>Die Codeliste enh채lt die einheitlichen Aufgabenfelder der allgemeinen Hochschulreife, die von der KMK festgelegt wurden. Quelle: https://www.kmk.org/fileadmin/Dateien/veroeffentlichungen_beschluesse/1974/1974_01_08-Zeugnis-Allg-Hochschulreife.pdf</xoev-cl-4:codelistDescription>
         <xoev-cl-4:agencyShortName>KMK</xoev-cl-4:agencyShortName>
         <xoev-cl-4:versionDescription>Die Art des Zeugnisses gibt an um welche Zeugnisart es sich handelt.</xoev-cl-4:versionDescription>
         <xoev-cl-4:validFrom>2022-01-31</xoev-cl-4:validFrom>
         <xoev-cl-4:versionHandbook>1.0</xoev-cl-4:versionHandbook>
      </Description>
   </Annotation>
   <Identification>
      <ShortName>Aufgabenfeld-Codes</ShortName>
      <LongName>Aufgabenfeld</LongName>
      <Version>1974</Version>
      <CanonicalUri>urn:xschule-digital:kmk:codeliste:aufgabenfeld</CanonicalUri>
      <CanonicalVersionUri>urn:xschule-digital:kmk:codeliste:aufgabenfeld_1974</CanonicalVersionUri>
      <Agency>
         <LongName>Kultusministerkonferenz</LongName>
      </Agency>
   </Identification>
   <ColumnSet>
      <Column Id="code" Use="required">
         <ShortName>code</ShortName>
         <LongName>Code</LongName>
         <Data Type="string"/>
      </Column>
      <Column Id="beschreibung" Use="required">
         <ShortName>beschreibung</ShortName>
         <Data Type="string"/>
      </Column>
      <Key Id="codeKey">
         <Annotation>
            <AppInfo>
               <xoev-cl-4:recommendedKeyColumn/>
            </AppInfo>
         </Annotation>
         <ShortName>codeKey</ShortName>
         <ColumnRef Ref="code"/>
      </Key>
   </ColumnSet>
   <SimpleCodeList>
      <Row>
         <Value ColumnRef="code">
            <SimpleValue>http://xschule.digital/def/kmk/1974/code/aufgabenfeld/10</SimpleValue>
         </Value>
         <Value ColumnRef="beschreibung">
            <SimpleValue>Sprachlich-literarisch-k체nstlerisches Aufgabenfeld</SimpleValue>
         </Value>
      </Row>
      <Row>
         <Value ColumnRef="code">
            <SimpleValue>http://xschule.digital/def/kmk/1974/code/aufgabenfeld/20</SimpleValue>
         </Value>
         <Value ColumnRef="beschreibung">
            <SimpleValue>Gesellschaftswissenschaftliches Aufgabenfeld</SimpleValue>
         </Value>
      </Row>
      <Row>
         <Value ColumnRef="code">
            <SimpleValue>http://xschule.digital/def/kmk/1974/code/aufgabenfeld/30</SimpleValue>
         </Value>
         <Value ColumnRef="beschreibung">
            <SimpleValue>Mathematischnaturwissenschaftlichtechnisches Aufgabenfeld</SimpleValue>
         </Value>
      </Row>
      <Row>
         <Value ColumnRef="code">
            <SimpleValue>http://xschule.digital/def/kmk/1974/code/aufgabenfeld/40</SimpleValue>
         </Value>
         <Value ColumnRef="beschreibung">
            <SimpleValue>Facharbeit</SimpleValue>
         </Value>
      </Row>
      <Row>
         <Value ColumnRef="code">
            <SimpleValue>http://xschule.digital/def/kmk/1974/code/aufgabenfeld/50</SimpleValue>
         </Value>
         <Value ColumnRef="beschreibung">
            <SimpleValue>Besondere Lernleistung</SimpleValue>
         </Value>
      </Row>
      <Row>
         <Value ColumnRef="code">
            <SimpleValue>http://xschule.digital/def/kmk/1974/code/aufgabenfeld/997</SimpleValue>
         </Value>
         <Value ColumnRef="beschreibung">
            <SimpleValue>Wert aus rechtlichen Gr체nden nicht 체bermittelt</SimpleValue>
         </Value>
      </Row>
      <Row>
         <Value ColumnRef="code">
            <SimpleValue>http://xschule.digital/def/kmk/1974/code/aufgabenfeld/998</SimpleValue>
         </Value>
         <Value ColumnRef="beschreibung">
            <SimpleValue>Wert nicht in Liste</SimpleValue>
         </Value>
      </Row>
      <Row>
         <Value ColumnRef="code">
            <SimpleValue>http://xschule.digital/def/kmk/1974/code/aufgabenfeld/999</SimpleValue>
         </Value>
         <Value ColumnRef="beschreibung">
            <SimpleValue>Wert nicht bekannt</SimpleValue>
         </Value>
      </Row>
   </SimpleCodeList>
</gc:CodeList>
